cvxpy_or/__init__.py
cvxpy_or/aggregations.py
cvxpy_or/constraints.py
cvxpy_or/display.py
cvxpy_or/model.py
cvxpy_or/pandas_io.py
cvxpy_or/sets.py
cvxpy_or/validation.py
cvxpy_or/xarray_io.py
cvxpy_or-0.1.0.dist-info/METADATA
cvxpy_or-0.1.0.dist-info/WHEEL
cvxpy_or-0.1.0.dist-info/licenses/LICENSE
cvxpy_or-0.1.0.dist-info/RECORD
