Metadata-Version: 2.4
Name: cvxpy-or
Version: 0.1.0
Summary: Operations Research-style modeling for CVXPY
License-Expression: Apache-2.0
License-File: LICENSE
Requires-Python: >=3.9
Requires-Dist: cvxpy>=1.7
Requires-Dist: numpy
Requires-Dist: pandas>=1.5
Requires-Dist: rich>=13.0
Requires-Dist: scipy
Provides-Extra: all
Requires-Dist: xarray>=2023.1.0; extra == 'all'
Provides-Extra: dev
Requires-Dist: pre-commit>=3.0; extra == 'dev'
Requires-Dist: pyright>=1.1.390; extra == 'dev'
Requires-Dist: pytest; extra == 'dev'
Requires-Dist: pytest-cov; extra == 'dev'
Requires-Dist: ruff>=0.1.0; extra == 'dev'
Requires-Dist: xarray>=2023.1.0; extra == 'dev'
Provides-Extra: docs
Requires-Dist: furo; extra == 'docs'
Requires-Dist: myst-parser; extra == 'docs'
Requires-Dist: sphinx-copybutton; extra == 'docs'
Requires-Dist: sphinx-design; extra == 'docs'
Requires-Dist: sphinx>=7.0; extra == 'docs'
Provides-Extra: lint
Requires-Dist: ruff>=0.1.0; extra == 'lint'
Provides-Extra: xarray
Requires-Dist: xarray>=2023.1.0; extra == 'xarray'
